arithmetic_bsr/__init__.py
arithmetic_bsr-0.1.dist-info/METADATA
arithmetic_bsr-0.1.dist-info/WHEEL
arithmetic_bsr-0.1.dist-info/top_level.txt
arithmetic_bsr-0.1.dist-info/RECORD
