Metadata-Version: 2.1
Name: arithmetic-bsr
Version: 0.1
Summary: perform simple arithmetics
Home-page: http://github.com/storborg/funniest
Author: Barun Singh
Author-email: bkumar@quadratyx.com
License: QTX
Platform: UNKNOWN
